{
    "group_aliases": {
        "a": "accessor_types"
    },
    "default_type": "VersionFileType",
    "client": {
        "allowed_accessor_types": ["a/download_client"],
        "must_exist": true,
        "available_when_unreleased": false
    },
    "server": {
        "allowed_accessor_types": ["a/download_server"],
        "must_exist": false,
        "available_when_unreleased": false
    },
    "json": {
        "allowed_accessor_types": ["a/download_json", "a/experimental_zip"],
        "must_exist": false,
        "available_when_unreleased": false
    },
    "experimental_data_pack": {
        "allowed_accessor_types": ["a/download_experimental_data_pack"],
        "must_exist": false,
        "available_when_unreleased": false
    }
}